{
  "schema_version": 2,
  "snapshot_date": "2026_04_02",
  "generated_at": "2026-04-02T03:33:29.710Z",
  "total_downloads": 16291,
  "raw_total_downloads": 20872,
  "total_attributed_downloads": 4581,
  "total_attributed_fetches": 4854,
  "net_downloads": 1010,
  "maps": {
    "downloads": {
      "albany": {
        "1.0.0": 64
      },
      "amsterdam": {
        "1.0.0": 168,
        "1.2.0": 150
      },
      "baltimore-dc-corridor": {
        "1.1.1": 96
      },
      "barcelona": {
        "1.0.0": 1,
        "1.0.1": 85
      },
      "bari": {
        "1.0.0": 60
      },
      "berlin-val": {
        "1.0.0": 229
      },
      "bilbao": {
        "1.0.0": 0,
        "1.0.1": 33
      },
      "bologna": {
        "1.0.0": 52
      },
      "bucharest-medium": {
        "v1.1.1": 37
      },
      "cairo": {
        "2.0.0": 16,
        "2.0.1": 56
      },
      "calgary": {
        "1.0.1": 64,
        "1.1.3": 153
      },
      "catania": {
        "1.0.0": 44
      },
      "colorado-ski-country": {
        "1.0.0": 79
      },
      "dayton-oh": {
        "1.0.0": 15,
        "1.1.0": 1
      },
      "daytonatti": {
        "1.0.0": 0
      },
      "dublin": {
        "v1.0.0": 108,
        "v1.1.0": 181
      },
      "edmonton": {
        "1.0.1": 51,
        "1.1.3": 139
      },
      "florence": {
        "1.0.0": 55
      },
      "garda-lake": {
        "1.0.0": 34
      },
      "genoa": {
        "1.0.0": 47
      },
      "glasgow-edinburgh": {
        "v1.0.0": 218
      },
      "greater-baltimore": {
        "1.1.0": 52
      },
      "greater-kuala-lumpur": {
        "v1.0.0": 83
      },
      "greater-los-angeles": {
        "1.0.1": 310
      },
      "greatertwincities": {
        "v1.0.0": 105
      },
      "jacksonville": {
        "1.0.0": 55
      },
      "jerusalem": {
        "v0.3.1": 93
      },
      "knoxville": {
        "1.1.0": 35,
        "1.1.1": 6
      },
      "los-angeles-county": {
        "1.0.0": 187
      },
      "louisville": {
        "1.0.0": 66
      },
      "madrid": {
        "1.0.0": 0,
        "1.0.1": 73
      },
      "memphis": {
        "1.1.0": 38
      },
      "mfn-hamptonroads": {
        "1.0.0": 96
      },
      "mfn-hong-kong": {
        "0.3.0": 2,
        "0.4.0": 376
      },
      "mfn-lasvegas": {
        "1.1.0": 81
      },
      "mfn-madisonwi": {
        "3.0.0": 120
      },
      "mfn-northwestar": {
        "1.0.0": 63
      },
      "milan": {
        "1.0.0": 173
      },
      "montreal": {
        "1.0.1": 81,
        "1.1.3": 406
      },
      "naples": {
        "1.0.0": 66
      },
      "nashville": {
        "2.0.0": 59
      },
      "oklahoma-city": {
        "1.0.0": 16
      },
      "orange-county": {
        "1.0.3": 64
      },
      "orlando": {
        "1.1.1": 44
      },
      "ottawa": {
        "1.0.1": 53,
        "1.1.3": 176
      },
      "palermo": {
        "1.0.0": 33
      },
      "pianura-emiliana": {
        "1.0.0": 21
      },
      "pianura-veneta": {
        "1.0.0": 39
      },
      "piedmont-triad": {
        "v1.0.0": 34
      },
      "providence": {
        "1.0.0": 81
      },
      "puerto-rico": {
        "1.0.1": 104
      },
      "quebec-city": {
        "1.0.1": 48,
        "1.1.3": 136
      },
      "richmond": {
        "1.1.0": 63
      },
      "riviera-romagnola": {
        "1.0.0": 21
      },
      "rochester": {
        "1.1.0": 55
      },
      "rome": {
        "1.0.0": 164
      },
      "rotterdam-the-hague": {
        "1.0.0": 91
      },
      "sacramento": {
        "1.0.0": 67
      },
      "san-antonio": {
        "1.1.1": 11
      },
      "san-juan": {
        "1.0.0": 45
      },
      "santa-barbara": {
        "1.0.1": 39
      },
      "singapore-val": {
        "1.0.0": 204
      },
      "spokane": {
        "1.0.0": 4,
        "2.0.0": 1,
        "2.1.0": 38
      },
      "sydney": {
        "1.0.0": 2,
        "1.1.0": 24,
        "1.2.0": 183
      },
      "tampa-bay": {
        "1.1.0": 92
      },
      "tel-aviv": {
        "v1.2.0": 1,
        "v1.3.0": 25,
        "v2.0.0": 101
      },
      "toronto": {
        "1.0.1": 132,
        "1.1.3": 551
      },
      "trondheim-val": {
        "1.0.0": 51
      },
      "turin": {
        "1.0.0": 49
      },
      "valencia": {
        "1.0.0": 0,
        "1.0.1": 35
      },
      "vancouver": {
        "1.0.1": 84,
        "1.1.3": 319
      },
      "warsaw-val": {
        "1.0.0": 99
      },
      "waterloo": {
        "1.0.0": 0,
        "1.0.1": 74,
        "1.1.0": 65
      },
      "wilmington-nc": {
        "v1.0.0": 18
      },
      "winnipeg": {
        "1.0.1": 49,
        "1.1.3": 118
      },
      "yukina-fukuoka": {
        "0.2.0": 71,
        "0.3.0": 51,
        "0.4.0": 70
      },
      "yukina-hakodate": {
        "0.1.0": 30,
        "0.2.0": 32
      },
      "yukina-hiroshima-kure": {
        "0.2.0": 59,
        "0.3.0": 36,
        "0.4.0": 55
      },
      "yukina-kagoshima-kirishima": {
        "0.2.0": 36,
        "0.3.0": 20,
        "0.4.0": 24
      },
      "yukina-kitakyushu-shimonoseki": {
        "0.2.0": 43,
        "0.3.0": 27,
        "0.4.0": 34
      },
      "yukina-kobe-akashi": {
        "0.2.0": 51,
        "0.3.0": 33,
        "0.4.0": 46
      },
      "yukina-kochi": {
        "0.2.0": 37,
        "0.3.0": 17,
        "0.4.0": 19
      },
      "yukina-kyoto": {
        "0.2.0": 130,
        "0.3.0": 87,
        "0.4.0": 114
      },
      "yukina-matsuyama": {
        "0.2.0": 47,
        "0.3.0": 27,
        "0.4.0": 21
      },
      "yukina-nagasaki": {
        "0.1.0": 24,
        "0.2.0": 28
      },
      "yukina-nagoya": {
        "0.1.4": 89
      },
      "yukina-nakaumi": {
        "0.1.0": 20,
        "0.2.0": 21
      },
      "yukina-niigata": {
        "0.2.0": 44,
        "0.3.0": 6,
        "0.4.0": 23
      },
      "yukina-okayama": {
        "0.1.0": 20
      },
      "yukina-okinawa": {
        "0.2.0": 59,
        "0.3.0": 26,
        "0.4.0": 61
      },
      "yukina-osaka": {
        "0.1.0": 68,
        "0.1.1": 58,
        "0.1.2": 170
      },
      "yukina-sapporo-chitose": {
        "0.2.0": 79,
        "0.3.0": 37,
        "0.4.0": 53
      },
      "yukina-sendai": {
        "0.2.0": 54,
        "0.3.0": 18,
        "0.4.0": 33
      },
      "yukina-takamatsu": {
        "0.1.0": 10,
        "0.2.0": 15
      },
      "yukina-toyama": {
        "0.1.0": 23,
        "0.2.0": 18
      },
      "yukina-yamagata": {
        "0.2.0": 41,
        "0.3.0": 10,
        "0.4.0": 20
      },
      "zurich": {
        "v1.0.0": 24,
        "v1.1.0": 310
      }
    },
    "raw_downloads": {
      "albany": {
        "1.0.0": 92
      },
      "amsterdam": {
        "1.0.0": 201,
        "1.2.0": 181
      },
      "baltimore-dc-corridor": {
        "1.1.1": 132
      },
      "barcelona": {
        "1.0.0": 2,
        "1.0.1": 91
      },
      "bari": {
        "1.0.0": 95
      },
      "berlin-val": {
        "1.0.0": 259
      },
      "bilbao": {
        "1.0.0": 1,
        "1.0.1": 39
      },
      "bologna": {
        "1.0.0": 87
      },
      "bucharest-medium": {
        "v1.1.1": 43
      },
      "cairo": {
        "2.0.0": 28,
        "2.0.1": 70
      },
      "calgary": {
        "1.0.1": 95,
        "1.1.3": 188
      },
      "catania": {
        "1.0.0": 79
      },
      "colorado-ski-country": {
        "1.0.0": 115
      },
      "dayton-oh": {
        "1.0.0": 21,
        "1.1.0": 3
      },
      "daytonatti": {
        "1.0.0": 2
      },
      "dublin": {
        "v1.0.0": 140,
        "v1.1.0": 217
      },
      "edmonton": {
        "1.0.1": 82,
        "1.1.3": 174
      },
      "florence": {
        "1.0.0": 90
      },
      "garda-lake": {
        "1.0.0": 62
      },
      "genoa": {
        "1.0.0": 82
      },
      "glasgow-edinburgh": {
        "v1.0.0": 227
      },
      "greater-baltimore": {
        "1.1.0": 87
      },
      "greater-kuala-lumpur": {
        "v1.0.0": 110
      },
      "greater-los-angeles": {
        "1.0.1": 346
      },
      "greatertwincities": {
        "v1.0.0": 141
      },
      "jacksonville": {
        "1.0.0": 90
      },
      "jerusalem": {
        "v0.3.1": 129
      },
      "knoxville": {
        "1.1.0": 66,
        "1.1.1": 12
      },
      "los-angeles-county": {
        "1.0.0": 223
      },
      "louisville": {
        "1.0.0": 102
      },
      "madrid": {
        "1.0.0": 1,
        "1.0.1": 79
      },
      "memphis": {
        "1.1.0": 73
      },
      "mfn-hamptonroads": {
        "1.0.0": 132
      },
      "mfn-hong-kong": {
        "0.3.0": 34,
        "0.4.0": 411
      },
      "mfn-lasvegas": {
        "1.1.0": 97
      },
      "mfn-madisonwi": {
        "3.0.0": 157
      },
      "mfn-northwestar": {
        "1.0.0": 99
      },
      "milan": {
        "1.0.0": 208
      },
      "montreal": {
        "1.0.1": 112,
        "1.1.3": 441
      },
      "naples": {
        "1.0.0": 101
      },
      "nashville": {
        "2.0.0": 95
      },
      "oklahoma-city": {
        "1.0.0": 22
      },
      "orange-county": {
        "1.0.3": 99
      },
      "orlando": {
        "1.1.1": 80
      },
      "ottawa": {
        "1.0.1": 84,
        "1.1.3": 211
      },
      "palermo": {
        "1.0.0": 68
      },
      "pianura-emiliana": {
        "1.0.0": 35
      },
      "pianura-veneta": {
        "1.0.0": 53
      },
      "piedmont-triad": {
        "v1.0.0": 42
      },
      "providence": {
        "1.0.0": 117
      },
      "puerto-rico": {
        "1.0.1": 131
      },
      "quebec-city": {
        "1.0.1": 79,
        "1.1.3": 171
      },
      "richmond": {
        "1.1.0": 98
      },
      "riviera-romagnola": {
        "1.0.0": 49
      },
      "rochester": {
        "1.1.0": 90
      },
      "rome": {
        "1.0.0": 199
      },
      "rotterdam-the-hague": {
        "1.0.0": 128
      },
      "sacramento": {
        "1.0.0": 103
      },
      "san-antonio": {
        "1.1.1": 46
      },
      "san-juan": {
        "1.0.0": 67
      },
      "santa-barbara": {
        "1.0.1": 74
      },
      "singapore-val": {
        "1.0.0": 234
      },
      "spokane": {
        "1.0.0": 8,
        "2.0.0": 5,
        "2.1.0": 46
      },
      "sydney": {
        "1.0.0": 17,
        "1.1.0": 39,
        "1.2.0": 201
      },
      "tampa-bay": {
        "1.1.0": 127
      },
      "tel-aviv": {
        "v1.2.0": 33,
        "v1.3.0": 57,
        "v2.0.0": 137
      },
      "toronto": {
        "1.0.1": 163,
        "1.1.3": 586
      },
      "trondheim-val": {
        "1.0.0": 81
      },
      "turin": {
        "1.0.0": 84
      },
      "valencia": {
        "1.0.0": 1,
        "1.0.1": 41
      },
      "vancouver": {
        "1.0.1": 115,
        "1.1.3": 354
      },
      "warsaw-val": {
        "1.0.0": 129
      },
      "waterloo": {
        "1.0.0": 32,
        "1.0.1": 106,
        "1.1.0": 90
      },
      "wilmington-nc": {
        "v1.0.0": 24
      },
      "winnipeg": {
        "1.0.1": 80,
        "1.1.3": 153
      },
      "yukina-fukuoka": {
        "0.2.0": 102,
        "0.3.0": 81,
        "0.4.0": 86
      },
      "yukina-hakodate": {
        "0.1.0": 60,
        "0.2.0": 48
      },
      "yukina-hiroshima-kure": {
        "0.2.0": 90,
        "0.3.0": 66,
        "0.4.0": 71
      },
      "yukina-kagoshima-kirishima": {
        "0.2.0": 67,
        "0.3.0": 50,
        "0.4.0": 40
      },
      "yukina-kitakyushu-shimonoseki": {
        "0.2.0": 74,
        "0.3.0": 57,
        "0.4.0": 50
      },
      "yukina-kobe-akashi": {
        "0.2.0": 82,
        "0.3.0": 63,
        "0.4.0": 62
      },
      "yukina-kochi": {
        "0.2.0": 68,
        "0.3.0": 47,
        "0.4.0": 35
      },
      "yukina-kyoto": {
        "0.2.0": 161,
        "0.3.0": 117,
        "0.4.0": 130
      },
      "yukina-matsuyama": {
        "0.2.0": 78,
        "0.3.0": 57,
        "0.4.0": 37
      },
      "yukina-nagasaki": {
        "0.1.0": 54,
        "0.2.0": 44
      },
      "yukina-nagoya": {
        "0.1.4": 97
      },
      "yukina-nakaumi": {
        "0.1.0": 50,
        "0.2.0": 37
      },
      "yukina-niigata": {
        "0.2.0": 75,
        "0.3.0": 36,
        "0.4.0": 39
      },
      "yukina-okayama": {
        "0.1.0": 36
      },
      "yukina-okinawa": {
        "0.2.0": 90,
        "0.3.0": 56,
        "0.4.0": 77
      },
      "yukina-osaka": {
        "0.1.0": 80,
        "0.1.1": 62,
        "0.1.2": 178
      },
      "yukina-sapporo-chitose": {
        "0.2.0": 110,
        "0.3.0": 67,
        "0.4.0": 69
      },
      "yukina-sendai": {
        "0.2.0": 85,
        "0.3.0": 48,
        "0.4.0": 49
      },
      "yukina-takamatsu": {
        "0.1.0": 40,
        "0.2.0": 31
      },
      "yukina-toyama": {
        "0.1.0": 53,
        "0.2.0": 34
      },
      "yukina-yamagata": {
        "0.2.0": 72,
        "0.3.0": 40,
        "0.4.0": 36
      },
      "zurich": {
        "v1.0.0": 56,
        "v1.1.0": 346
      }
    },
    "attributed_downloads": {
      "albany": {
        "1.0.0": 28
      },
      "amsterdam": {
        "1.0.0": 33,
        "1.2.0": 31
      },
      "baltimore-dc-corridor": {
        "1.1.1": 36
      },
      "barcelona": {
        "1.0.0": 1,
        "1.0.1": 6
      },
      "bari": {
        "1.0.0": 35
      },
      "berlin-val": {
        "1.0.0": 30
      },
      "bilbao": {
        "1.0.0": 1,
        "1.0.1": 6
      },
      "bologna": {
        "1.0.0": 35
      },
      "bucharest-medium": {
        "v1.1.1": 6
      },
      "cairo": {
        "2.0.0": 12,
        "2.0.1": 14
      },
      "calgary": {
        "1.0.1": 31,
        "1.1.3": 35
      },
      "catania": {
        "1.0.0": 35
      },
      "colorado-ski-country": {
        "1.0.0": 36
      },
      "dayton-oh": {
        "1.0.0": 6,
        "1.1.0": 2
      },
      "daytonatti": {
        "1.0.0": 2
      },
      "dublin": {
        "v1.0.0": 32,
        "v1.1.0": 36
      },
      "edmonton": {
        "1.0.1": 31,
        "1.1.3": 35
      },
      "florence": {
        "1.0.0": 35
      },
      "garda-lake": {
        "1.0.0": 28
      },
      "genoa": {
        "1.0.0": 35
      },
      "glasgow-edinburgh": {
        "v1.0.0": 9
      },
      "greater-baltimore": {
        "1.1.0": 35
      },
      "greater-kuala-lumpur": {
        "v1.0.0": 27
      },
      "greater-los-angeles": {
        "1.0.1": 36
      },
      "greatertwincities": {
        "v1.0.0": 36
      },
      "jacksonville": {
        "1.0.0": 35
      },
      "jerusalem": {
        "v0.3.1": 36
      },
      "knoxville": {
        "1.1.0": 31,
        "1.1.1": 6
      },
      "los-angeles-county": {
        "1.0.0": 36
      },
      "louisville": {
        "1.0.0": 36
      },
      "madrid": {
        "1.0.0": 1,
        "1.0.1": 6
      },
      "memphis": {
        "1.1.0": 35
      },
      "mfn-hamptonroads": {
        "1.0.0": 36
      },
      "mfn-hong-kong": {
        "0.3.0": 32,
        "0.4.0": 35
      },
      "mfn-lasvegas": {
        "1.1.0": 16
      },
      "mfn-madisonwi": {
        "3.0.0": 37
      },
      "mfn-northwestar": {
        "1.0.0": 36
      },
      "milan": {
        "1.0.0": 35
      },
      "montreal": {
        "1.0.1": 31,
        "1.1.3": 35
      },
      "naples": {
        "1.0.0": 35
      },
      "nashville": {
        "2.0.0": 36
      },
      "oklahoma-city": {
        "1.0.0": 6
      },
      "orange-county": {
        "1.0.3": 35
      },
      "orlando": {
        "1.1.1": 36
      },
      "ottawa": {
        "1.0.1": 31,
        "1.1.3": 35
      },
      "palermo": {
        "1.0.0": 35
      },
      "pianura-emiliana": {
        "1.0.0": 14
      },
      "pianura-veneta": {
        "1.0.0": 14
      },
      "piedmont-triad": {
        "v1.0.0": 8
      },
      "providence": {
        "1.0.0": 36
      },
      "puerto-rico": {
        "1.0.1": 27
      },
      "quebec-city": {
        "1.0.1": 31,
        "1.1.3": 35
      },
      "richmond": {
        "1.1.0": 35
      },
      "riviera-romagnola": {
        "1.0.0": 28
      },
      "rochester": {
        "1.1.0": 35
      },
      "rome": {
        "1.0.0": 35
      },
      "rotterdam-the-hague": {
        "1.0.0": 37
      },
      "sacramento": {
        "1.0.0": 36
      },
      "san-antonio": {
        "1.1.1": 35
      },
      "san-juan": {
        "1.0.0": 22
      },
      "santa-barbara": {
        "1.0.1": 35
      },
      "singapore-val": {
        "1.0.0": 30
      },
      "spokane": {
        "1.0.0": 4,
        "2.0.0": 4,
        "2.1.0": 8
      },
      "sydney": {
        "1.0.0": 15,
        "1.1.0": 15,
        "1.2.0": 18
      },
      "tampa-bay": {
        "1.1.0": 35
      },
      "tel-aviv": {
        "v1.2.0": 32,
        "v1.3.0": 32,
        "v2.0.0": 36
      },
      "toronto": {
        "1.0.1": 31,
        "1.1.3": 35
      },
      "trondheim-val": {
        "1.0.0": 30
      },
      "turin": {
        "1.0.0": 35
      },
      "valencia": {
        "1.0.0": 1,
        "1.0.1": 6
      },
      "vancouver": {
        "1.0.1": 31,
        "1.1.3": 35
      },
      "warsaw-val": {
        "1.0.0": 30
      },
      "waterloo": {
        "1.0.0": 32,
        "1.0.1": 32,
        "1.1.0": 25
      },
      "wilmington-nc": {
        "v1.0.0": 6
      },
      "winnipeg": {
        "1.0.1": 31,
        "1.1.3": 35
      },
      "yukina-fukuoka": {
        "0.2.0": 31,
        "0.3.0": 30,
        "0.4.0": 16
      },
      "yukina-hakodate": {
        "0.1.0": 30,
        "0.2.0": 16
      },
      "yukina-hiroshima-kure": {
        "0.2.0": 31,
        "0.3.0": 30,
        "0.4.0": 16
      },
      "yukina-kagoshima-kirishima": {
        "0.2.0": 31,
        "0.3.0": 30,
        "0.4.0": 16
      },
      "yukina-kitakyushu-shimonoseki": {
        "0.2.0": 31,
        "0.3.0": 30,
        "0.4.0": 16
      },
      "yukina-kobe-akashi": {
        "0.2.0": 31,
        "0.3.0": 30,
        "0.4.0": 16
      },
      "yukina-kochi": {
        "0.2.0": 31,
        "0.3.0": 30,
        "0.4.0": 16
      },
      "yukina-kyoto": {
        "0.2.0": 31,
        "0.3.0": 30,
        "0.4.0": 16
      },
      "yukina-matsuyama": {
        "0.2.0": 31,
        "0.3.0": 30,
        "0.4.0": 16
      },
      "yukina-nagasaki": {
        "0.1.0": 30,
        "0.2.0": 16
      },
      "yukina-nagoya": {
        "0.1.4": 8
      },
      "yukina-nakaumi": {
        "0.1.0": 30,
        "0.2.0": 16
      },
      "yukina-niigata": {
        "0.2.0": 31,
        "0.3.0": 30,
        "0.4.0": 16
      },
      "yukina-okayama": {
        "0.1.0": 16
      },
      "yukina-okinawa": {
        "0.2.0": 31,
        "0.3.0": 30,
        "0.4.0": 16
      },
      "yukina-osaka": {
        "0.1.0": 12,
        "0.1.1": 4,
        "0.1.2": 8
      },
      "yukina-sapporo-chitose": {
        "0.2.0": 31,
        "0.3.0": 30,
        "0.4.0": 16
      },
      "yukina-sendai": {
        "0.2.0": 31,
        "0.3.0": 30,
        "0.4.0": 16
      },
      "yukina-takamatsu": {
        "0.1.0": 30,
        "0.2.0": 16
      },
      "yukina-toyama": {
        "0.1.0": 30,
        "0.2.0": 16
      },
      "yukina-yamagata": {
        "0.2.0": 31,
        "0.3.0": 30,
        "0.4.0": 16
      },
      "zurich": {
        "v1.0.0": 32,
        "v1.1.0": 36
      }
    },
    "total_downloads": 11265,
    "raw_total_downloads": 15259,
    "total_attributed_downloads": 3994,
    "net_downloads": 590,
    "source_downloads_mode": "already_adjusted",
    "index": {
      "schema_version": 1,
      "maps": [
        "albany",
        "amsterdam",
        "baltimore-dc-corridor",
        "barcelona",
        "bari",
        "berlin-val",
        "bilbao",
        "bologna",
        "bucharest-medium",
        "cairo",
        "calgary",
        "catania",
        "colorado-ski-country",
        "dayton-oh",
        "daytonatti",
        "dublin",
        "edmonton",
        "florence",
        "garda-lake",
        "genoa",
        "glasgow-edinburgh",
        "greater-baltimore",
        "greater-kuala-lumpur",
        "greater-los-angeles",
        "greatertwincities",
        "jacksonville",
        "jerusalem",
        "knoxville",
        "los-angeles-county",
        "louisville",
        "madrid",
        "memphis",
        "mfn-hamptonroads",
        "mfn-hong-kong",
        "mfn-lasvegas",
        "mfn-madisonwi",
        "mfn-northwestar",
        "milan",
        "montreal",
        "naples",
        "nashville",
        "oklahoma-city",
        "orange-county",
        "orlando",
        "ottawa",
        "palermo",
        "pianura-emiliana",
        "pianura-veneta",
        "piedmont-triad",
        "providence",
        "puerto-rico",
        "quebec-city",
        "richmond",
        "riviera-romagnola",
        "rochester",
        "rome",
        "rotterdam-the-hague",
        "sacramento",
        "san-antonio",
        "san-juan",
        "santa-barbara",
        "singapore-val",
        "spokane",
        "sydney",
        "tampa-bay",
        "tel-aviv",
        "toronto",
        "trondheim-val",
        "turin",
        "valencia",
        "vancouver",
        "warsaw-val",
        "waterloo",
        "wilmington-nc",
        "winnipeg",
        "yukina-fukuoka",
        "yukina-hakodate",
        "yukina-hiroshima-kure",
        "yukina-kagoshima-kirishima",
        "yukina-kitakyushu-shimonoseki",
        "yukina-kobe-akashi",
        "yukina-kochi",
        "yukina-kyoto",
        "yukina-matsuyama",
        "yukina-nagasaki",
        "yukina-nagoya",
        "yukina-nakaumi",
        "yukina-niigata",
        "yukina-okayama",
        "yukina-okinawa",
        "yukina-osaka",
        "yukina-sapporo-chitose",
        "yukina-sendai",
        "yukina-takamatsu",
        "yukina-toyama",
        "yukina-yamagata",
        "zurich"
      ]
    },
    "entries": 97
  },
  "mods": {
    "downloads": {
      "advanced-analytics": {
        "v1.1.0": 549,
        "v1.2.0": 38,
        "v1.2.1": 300,
        "v1.2.5": 36,
        "v1.2.6": 1,
        "v1.2.7": 106,
        "v1.2.8": 118,
        "v1.2.9": 93,
        "v1.3.0": 78,
        "v1.3.1": 169,
        "v1.3.2": 182
      },
      "any-money": {
        "v0.1.0": 37,
        "v0.1.1": 99,
        "v0.2.0": 170
      },
      "cinematic-camera": {
        "v1.0.0": 11,
        "v1.1.0": 16,
        "v1.2.0": 207
      },
      "citymapper": {
        "0.1.2": 264
      },
      "danield1909-dantrains": {
        "v1.0.0": 15,
        "v1.0.1": 53,
        "v1.0.2": 80,
        "v1.0.3": 42,
        "v1.1.0": 26,
        "v1.1.1": 46,
        "v1.1.2": 21,
        "v1.2.0": 22,
        "v1.2.1": 62,
        "v1.3.0": 244
      },
      "dep-test-mod": {
        "0.1.3": 5
      },
      "dep-test-mod-nested": {
        "0.1.0": 10
      },
      "distance-circles": {
        "0.3.3": 199,
        "0.4.0": 323
      },
      "simple-trains": {},
      "station-dots": {
        "v1.0.0": 8
      },
      "subwaybuilder-regions": {
        "v0.4.5": 484
      },
      "test-mod-vulnscan": {},
      "transit-overlay": {
        "1.5.0": 446
      },
      "valdotoriums-trains": {
        "v0.1.3": 280,
        "v0.1.4": 186
      }
    },
    "raw_downloads": {
      "advanced-analytics": {
        "v1.1.0": 579,
        "v1.2.0": 65,
        "v1.2.1": 326,
        "v1.2.5": 48,
        "v1.2.6": 10,
        "v1.2.7": 115,
        "v1.2.8": 121,
        "v1.2.9": 96,
        "v1.3.0": 80,
        "v1.3.1": 170,
        "v1.3.2": 183
      },
      "any-money": {
        "v0.1.0": 56,
        "v0.1.1": 117,
        "v0.2.0": 173
      },
      "cinematic-camera": {
        "v1.0.0": 32,
        "v1.1.0": 34,
        "v1.2.0": 218
      },
      "citymapper": {
        "0.1.2": 290
      },
      "danield1909-dantrains": {
        "v1.0.0": 46,
        "v1.0.1": 81,
        "v1.0.2": 108,
        "v1.0.3": 66,
        "v1.1.0": 47,
        "v1.1.1": 65,
        "v1.1.2": 36,
        "v1.2.0": 35,
        "v1.2.1": 72,
        "v1.3.0": 250
      },
      "dep-test-mod": {
        "0.1.3": 12
      },
      "dep-test-mod-nested": {
        "0.1.0": 17
      },
      "distance-circles": {
        "0.3.3": 229,
        "0.4.0": 340
      },
      "simple-trains": {},
      "station-dots": {
        "v1.0.0": 9
      },
      "subwaybuilder-regions": {
        "v0.4.5": 514
      },
      "test-mod-vulnscan": {},
      "transit-overlay": {
        "1.5.0": 476
      },
      "valdotoriums-trains": {
        "v0.1.3": 308,
        "v0.1.4": 189
      }
    },
    "attributed_downloads": {
      "advanced-analytics": {
        "v1.1.0": 30,
        "v1.2.0": 27,
        "v1.2.1": 26,
        "v1.2.5": 12,
        "v1.2.6": 9,
        "v1.2.7": 9,
        "v1.2.8": 3,
        "v1.2.9": 3,
        "v1.3.0": 2,
        "v1.3.1": 1,
        "v1.3.2": 1
      },
      "any-money": {
        "v0.1.0": 19,
        "v0.1.1": 18,
        "v0.2.0": 3
      },
      "cinematic-camera": {
        "v1.0.0": 21,
        "v1.1.0": 18,
        "v1.2.0": 11
      },
      "citymapper": {
        "0.1.2": 26
      },
      "danield1909-dantrains": {
        "v1.0.0": 31,
        "v1.0.1": 28,
        "v1.0.2": 28,
        "v1.0.3": 24,
        "v1.1.0": 21,
        "v1.1.1": 19,
        "v1.1.2": 15,
        "v1.2.0": 13,
        "v1.2.1": 10,
        "v1.3.0": 6
      },
      "dep-test-mod": {
        "0.1.3": 7
      },
      "dep-test-mod-nested": {
        "0.1.0": 7
      },
      "distance-circles": {
        "0.3.3": 30,
        "0.4.0": 17
      },
      "simple-trains": {},
      "station-dots": {
        "v1.0.0": 1
      },
      "subwaybuilder-regions": {
        "v0.4.5": 30
      },
      "test-mod-vulnscan": {},
      "transit-overlay": {
        "1.5.0": 30
      },
      "valdotoriums-trains": {
        "v0.1.3": 28,
        "v0.1.4": 3
      }
    },
    "total_downloads": 5026,
    "raw_total_downloads": 5613,
    "total_attributed_downloads": 587,
    "net_downloads": 420,
    "source_downloads_mode": "already_adjusted",
    "index": {
      "schema_version": 1,
      "mods": [
        "advanced-analytics",
        "any-money",
        "cinematic-camera",
        "citymapper",
        "danield1909-dantrains",
        "dep-test-mod",
        "dep-test-mod-nested",
        "distance-circles",
        "simple-trains",
        "station-dots",
        "subwaybuilder-regions",
        "test-mod-vulnscan",
        "transit-overlay",
        "valdotoriums-trains"
      ]
    },
    "entries": 14
  }
}
