{
  "schema_version": 2,
  "snapshot_date": "2026_04_04",
  "generated_at": "2026-04-04T03:22:40.737Z",
  "total_downloads": 18331,
  "raw_total_downloads": 22842,
  "total_attributed_downloads": 4511,
  "total_attributed_fetches": 4785,
  "net_downloads": 1044,
  "maps": {
    "downloads": {
      "albany": {
        "1.0.0": 45
      },
      "amsterdam": {
        "1.0.0": 172,
        "1.2.0": 168
      },
      "anchorage-ak": {
        "1.0.0": 7
      },
      "baltimore-dc-corridor": {
        "1.1.1": 119
      },
      "barcelona": {
        "1.0.0": 1,
        "1.0.1": 137
      },
      "bari": {
        "1.0.0": 63
      },
      "berlin-val": {
        "1.0.0": 261
      },
      "bilbao": {
        "1.0.0": 0,
        "1.0.1": 46
      },
      "bologna": {
        "1.0.0": 49
      },
      "bucharest-medium": {
        "v1.1.1": 68
      },
      "cairo": {
        "2.0.0": 18,
        "2.0.1": 54
      },
      "calgary": {
        "1.0.1": 64,
        "1.1.3": 156
      },
      "catania": {
        "1.0.0": 47
      },
      "charleston-huntington-wv": {},
      "colorado-ski-country": {
        "1.0.0": 49
      },
      "dayton-oh": {
        "1.0.0": 14,
        "1.1.0": 7
      },
      "daytonatti": {
        "1.0.0": 12
      },
      "dublin": {
        "v1.0.0": 108,
        "v1.1.0": 164
      },
      "edmonton": {
        "1.0.1": 51,
        "1.1.3": 140
      },
      "florence": {
        "1.0.0": 52
      },
      "garda-lake": {
        "1.0.0": 31
      },
      "genoa": {
        "1.0.0": 50
      },
      "glasgow-edinburgh": {
        "v1.0.0": 249
      },
      "greater-baltimore": {
        "1.1.0": 48
      },
      "greater-kuala-lumpur": {
        "v1.0.0": 68
      },
      "greater-los-angeles": {
        "1.0.1": 343
      },
      "greatertwincities": {
        "v1.0.0": 76
      },
      "jacksonville": {
        "1.0.0": 52
      },
      "jerusalem": {
        "v0.3.1": 63
      },
      "knoxville": {
        "1.1.0": 39,
        "1.1.1": 2
      },
      "los-angeles-county": {
        "1.0.0": 195
      },
      "louisville": {
        "1.0.0": 36
      },
      "madrid": {
        "1.0.0": 1,
        "1.0.1": 131
      },
      "memphis": {
        "1.1.0": 37
      },
      "mfn-hamptonroads": {
        "1.0.0": 73
      },
      "mfn-hong-kong": {
        "0.3.0": 2,
        "0.4.0": 382
      },
      "mfn-lasvegas": {
        "1.1.0": 78
      },
      "mfn-madisonwi": {
        "3.0.0": 92
      },
      "mfn-northwestar": {
        "1.0.0": 34
      },
      "milan": {
        "1.0.0": 188
      },
      "monterrey": {
        "1.0.0": 13
      },
      "montreal": {
        "1.0.1": 81,
        "1.1.3": 418
      },
      "naples": {
        "1.0.0": 70
      },
      "nashville": {
        "2.0.0": 28
      },
      "oklahoma-city": {
        "1.0.0": 21
      },
      "orange-county": {
        "1.0.3": 62
      },
      "orlando": {
        "1.1.1": 55
      },
      "ottawa": {
        "1.0.1": 53,
        "1.1.3": 177
      },
      "palermo": {
        "1.0.0": 31
      },
      "pianura-emiliana": {
        "1.0.0": 19
      },
      "pianura-veneta": {
        "1.0.0": 37
      },
      "piedmont-triad": {
        "v1.0.0": 32
      },
      "providence": {
        "1.0.0": 51
      },
      "puerto-rico": {
        "1.0.1": 111
      },
      "quebec-city": {
        "1.0.1": 48,
        "1.1.3": 135
      },
      "richmond": {
        "1.1.0": 60
      },
      "riviera-romagnola": {
        "1.0.0": 18
      },
      "rochester": {
        "1.1.0": 52
      },
      "rome": {
        "1.0.0": 174
      },
      "rotterdam-the-hague": {
        "1.0.0": 94
      },
      "sacramento": {
        "1.0.0": 36
      },
      "san-antonio": {
        "1.1.1": 24
      },
      "san-juan": {
        "1.0.0": 44
      },
      "santa-barbara": {
        "1.0.1": 39
      },
      "singapore-val": {
        "1.0.0": 220
      },
      "south-florida": {
        "v1.0.0": 0
      },
      "spokane": {
        "1.0.0": 4,
        "2.0.0": 1,
        "2.1.0": 39
      },
      "sydney": {
        "1.0.0": 2,
        "1.1.0": 24,
        "1.2.0": 190
      },
      "tampa-bay": {
        "1.1.0": 97
      },
      "tel-aviv": {
        "v1.2.0": 1,
        "v1.3.0": 26,
        "v2.0.0": 74
      },
      "toronto": {
        "1.0.1": 133,
        "1.1.3": 579
      },
      "trondheim-val": {
        "1.0.0": 50
      },
      "turin": {
        "1.0.0": 47
      },
      "valencia": {
        "1.0.0": 0,
        "1.0.1": 43
      },
      "vancouver": {
        "1.0.1": 84,
        "1.1.3": 331
      },
      "warsaw-val": {
        "1.0.0": 97
      },
      "waterloo": {
        "1.0.0": 0,
        "1.0.1": 76,
        "1.1.0": 37
      },
      "wilmington-nc": {
        "v1.0.0": 22
      },
      "winnipeg": {
        "1.0.1": 49,
        "1.1.3": 117
      },
      "yukina-fukuoka": {
        "0.2.0": 73,
        "0.3.0": 51,
        "0.4.0": 75
      },
      "yukina-hakodate": {
        "0.1.0": 30,
        "0.2.0": 26
      },
      "yukina-hiroshima-kure": {
        "0.2.0": 60,
        "0.3.0": 37,
        "0.4.0": 52
      },
      "yukina-kagoshima-kirishima": {
        "0.2.0": 37,
        "0.3.0": 20,
        "0.4.0": 19
      },
      "yukina-kitakyushu-shimonoseki": {
        "0.2.0": 44,
        "0.3.0": 27,
        "0.4.0": 31
      },
      "yukina-kobe-akashi": {
        "0.2.0": 52,
        "0.3.0": 33,
        "0.4.0": 48
      },
      "yukina-kochi": {
        "0.2.0": 38,
        "0.3.0": 17,
        "0.4.0": 14
      },
      "yukina-kyoto": {
        "0.2.0": 133,
        "0.3.0": 90,
        "0.4.0": 125
      },
      "yukina-matsuyama": {
        "0.2.0": 48,
        "0.3.0": 27,
        "0.4.0": 14
      },
      "yukina-nagasaki": {
        "0.1.0": 24,
        "0.2.0": 24
      },
      "yukina-nagoya": {
        "0.1.4": 107
      },
      "yukina-nakaumi": {
        "0.1.0": 20,
        "0.2.0": 15
      },
      "yukina-niigata": {
        "0.2.0": 45,
        "0.3.0": 6,
        "0.4.0": 19
      },
      "yukina-okayama": {
        "0.1.0": 18
      },
      "yukina-okinawa": {
        "0.2.0": 60,
        "0.3.0": 26,
        "0.4.0": 60
      },
      "yukina-osaka": {
        "0.1.0": 71,
        "0.1.1": 59,
        "0.1.2": 207
      },
      "yukina-sapporo-chitose": {
        "0.2.0": 80,
        "0.3.0": 38,
        "0.4.0": 54
      },
      "yukina-sendai": {
        "0.2.0": 55,
        "0.3.0": 20,
        "0.4.0": 30
      },
      "yukina-takamatsu": {
        "0.1.0": 10,
        "0.2.0": 10
      },
      "yukina-toyama": {
        "0.1.0": 23,
        "0.2.0": 11
      },
      "yukina-yamagata": {
        "0.2.0": 42,
        "0.3.0": 10,
        "0.4.0": 16
      },
      "zurich": {
        "v1.0.0": 24,
        "v1.1.0": 296
      }
    },
    "raw_downloads": {
      "albany": {
        "1.0.0": 73
      },
      "amsterdam": {
        "1.0.0": 203,
        "1.2.0": 197
      },
      "anchorage-ak": {
        "1.0.0": 9
      },
      "baltimore-dc-corridor": {
        "1.1.1": 144
      },
      "barcelona": {
        "1.0.0": 2,
        "1.0.1": 143
      },
      "bari": {
        "1.0.0": 92
      },
      "berlin-val": {
        "1.0.0": 291
      },
      "bilbao": {
        "1.0.0": 1,
        "1.0.1": 52
      },
      "bologna": {
        "1.0.0": 84
      },
      "bucharest-medium": {
        "v1.1.1": 74
      },
      "cairo": {
        "2.0.0": 28,
        "2.0.1": 68
      },
      "calgary": {
        "1.0.1": 95,
        "1.1.3": 191
      },
      "catania": {
        "1.0.0": 76
      },
      "charleston-huntington-wv": {},
      "colorado-ski-country": {
        "1.0.0": 85
      },
      "dayton-oh": {
        "1.0.0": 20,
        "1.1.0": 9
      },
      "daytonatti": {
        "1.0.0": 14
      },
      "dublin": {
        "v1.0.0": 140,
        "v1.1.0": 200
      },
      "edmonton": {
        "1.0.1": 82,
        "1.1.3": 175
      },
      "florence": {
        "1.0.0": 87
      },
      "garda-lake": {
        "1.0.0": 59
      },
      "genoa": {
        "1.0.0": 79
      },
      "glasgow-edinburgh": {
        "v1.0.0": 258
      },
      "greater-baltimore": {
        "1.1.0": 83
      },
      "greater-kuala-lumpur": {
        "v1.0.0": 95
      },
      "greater-los-angeles": {
        "1.0.1": 379
      },
      "greatertwincities": {
        "v1.0.0": 112
      },
      "jacksonville": {
        "1.0.0": 87
      },
      "jerusalem": {
        "v0.3.1": 99
      },
      "knoxville": {
        "1.1.0": 70,
        "1.1.1": 8
      },
      "los-angeles-county": {
        "1.0.0": 231
      },
      "louisville": {
        "1.0.0": 72
      },
      "madrid": {
        "1.0.0": 2,
        "1.0.1": 137
      },
      "memphis": {
        "1.1.0": 72
      },
      "mfn-hamptonroads": {
        "1.0.0": 109
      },
      "mfn-hong-kong": {
        "0.3.0": 34,
        "0.4.0": 417
      },
      "mfn-lasvegas": {
        "1.1.0": 94
      },
      "mfn-madisonwi": {
        "3.0.0": 129
      },
      "mfn-northwestar": {
        "1.0.0": 70
      },
      "milan": {
        "1.0.0": 216
      },
      "monterrey": {
        "1.0.0": 15
      },
      "montreal": {
        "1.0.1": 112,
        "1.1.3": 453
      },
      "naples": {
        "1.0.0": 99
      },
      "nashville": {
        "2.0.0": 64
      },
      "oklahoma-city": {
        "1.0.0": 27
      },
      "orange-county": {
        "1.0.3": 97
      },
      "orlando": {
        "1.1.1": 80
      },
      "ottawa": {
        "1.0.1": 84,
        "1.1.3": 212
      },
      "palermo": {
        "1.0.0": 66
      },
      "pianura-emiliana": {
        "1.0.0": 33
      },
      "pianura-veneta": {
        "1.0.0": 51
      },
      "piedmont-triad": {
        "v1.0.0": 40
      },
      "providence": {
        "1.0.0": 87
      },
      "puerto-rico": {
        "1.0.1": 134
      },
      "quebec-city": {
        "1.0.1": 79,
        "1.1.3": 170
      },
      "richmond": {
        "1.1.0": 95
      },
      "riviera-romagnola": {
        "1.0.0": 46
      },
      "rochester": {
        "1.1.0": 87
      },
      "rome": {
        "1.0.0": 209
      },
      "rotterdam-the-hague": {
        "1.0.0": 129
      },
      "sacramento": {
        "1.0.0": 72
      },
      "san-antonio": {
        "1.1.1": 47
      },
      "san-juan": {
        "1.0.0": 66
      },
      "santa-barbara": {
        "1.0.1": 74
      },
      "singapore-val": {
        "1.0.0": 250
      },
      "south-florida": {
        "v1.0.0": 2
      },
      "spokane": {
        "1.0.0": 8,
        "2.0.0": 5,
        "2.1.0": 47
      },
      "sydney": {
        "1.0.0": 17,
        "1.1.0": 39,
        "1.2.0": 208
      },
      "tampa-bay": {
        "1.1.0": 132
      },
      "tel-aviv": {
        "v1.2.0": 33,
        "v1.3.0": 58,
        "v2.0.0": 110
      },
      "toronto": {
        "1.0.1": 164,
        "1.1.3": 614
      },
      "trondheim-val": {
        "1.0.0": 80
      },
      "turin": {
        "1.0.0": 82
      },
      "valencia": {
        "1.0.0": 1,
        "1.0.1": 49
      },
      "vancouver": {
        "1.0.1": 115,
        "1.1.3": 366
      },
      "warsaw-val": {
        "1.0.0": 127
      },
      "waterloo": {
        "1.0.0": 32,
        "1.0.1": 108,
        "1.1.0": 62
      },
      "wilmington-nc": {
        "v1.0.0": 28
      },
      "winnipeg": {
        "1.0.1": 80,
        "1.1.3": 152
      },
      "yukina-fukuoka": {
        "0.2.0": 104,
        "0.3.0": 81,
        "0.4.0": 91
      },
      "yukina-hakodate": {
        "0.1.0": 60,
        "0.2.0": 42
      },
      "yukina-hiroshima-kure": {
        "0.2.0": 91,
        "0.3.0": 67,
        "0.4.0": 68
      },
      "yukina-kagoshima-kirishima": {
        "0.2.0": 68,
        "0.3.0": 50,
        "0.4.0": 35
      },
      "yukina-kitakyushu-shimonoseki": {
        "0.2.0": 75,
        "0.3.0": 57,
        "0.4.0": 47
      },
      "yukina-kobe-akashi": {
        "0.2.0": 83,
        "0.3.0": 63,
        "0.4.0": 64
      },
      "yukina-kochi": {
        "0.2.0": 69,
        "0.3.0": 47,
        "0.4.0": 30
      },
      "yukina-kyoto": {
        "0.2.0": 164,
        "0.3.0": 120,
        "0.4.0": 141
      },
      "yukina-matsuyama": {
        "0.2.0": 79,
        "0.3.0": 57,
        "0.4.0": 30
      },
      "yukina-nagasaki": {
        "0.1.0": 54,
        "0.2.0": 40
      },
      "yukina-nagoya": {
        "0.1.4": 115
      },
      "yukina-nakaumi": {
        "0.1.0": 50,
        "0.2.0": 31
      },
      "yukina-niigata": {
        "0.2.0": 76,
        "0.3.0": 36,
        "0.4.0": 35
      },
      "yukina-okayama": {
        "0.1.0": 34
      },
      "yukina-okinawa": {
        "0.2.0": 91,
        "0.3.0": 56,
        "0.4.0": 76
      },
      "yukina-osaka": {
        "0.1.0": 83,
        "0.1.1": 63,
        "0.1.2": 215
      },
      "yukina-sapporo-chitose": {
        "0.2.0": 111,
        "0.3.0": 68,
        "0.4.0": 70
      },
      "yukina-sendai": {
        "0.2.0": 86,
        "0.3.0": 50,
        "0.4.0": 46
      },
      "yukina-takamatsu": {
        "0.1.0": 40,
        "0.2.0": 26
      },
      "yukina-toyama": {
        "0.1.0": 53,
        "0.2.0": 27
      },
      "yukina-yamagata": {
        "0.2.0": 73,
        "0.3.0": 40,
        "0.4.0": 32
      },
      "zurich": {
        "v1.0.0": 56,
        "v1.1.0": 332
      }
    },
    "attributed_downloads": {
      "albany": {
        "1.0.0": 28
      },
      "amsterdam": {
        "1.0.0": 31,
        "1.2.0": 29
      },
      "anchorage-ak": {
        "1.0.0": 2
      },
      "baltimore-dc-corridor": {
        "1.1.1": 25
      },
      "barcelona": {
        "1.0.0": 1,
        "1.0.1": 6
      },
      "bari": {
        "1.0.0": 29
      },
      "berlin-val": {
        "1.0.0": 30
      },
      "bilbao": {
        "1.0.0": 1,
        "1.0.1": 6
      },
      "bologna": {
        "1.0.0": 35
      },
      "bucharest-medium": {
        "v1.1.1": 6
      },
      "cairo": {
        "2.0.0": 10,
        "2.0.1": 14
      },
      "calgary": {
        "1.0.1": 31,
        "1.1.3": 35
      },
      "catania": {
        "1.0.0": 29
      },
      "charleston-huntington-wv": {},
      "colorado-ski-country": {
        "1.0.0": 36
      },
      "dayton-oh": {
        "1.0.0": 6,
        "1.1.0": 2
      },
      "daytonatti": {
        "1.0.0": 2
      },
      "dublin": {
        "v1.0.0": 32,
        "v1.1.0": 36
      },
      "edmonton": {
        "1.0.1": 31,
        "1.1.3": 35
      },
      "florence": {
        "1.0.0": 35
      },
      "garda-lake": {
        "1.0.0": 28
      },
      "genoa": {
        "1.0.0": 29
      },
      "glasgow-edinburgh": {
        "v1.0.0": 9
      },
      "greater-baltimore": {
        "1.1.0": 35
      },
      "greater-kuala-lumpur": {
        "v1.0.0": 27
      },
      "greater-los-angeles": {
        "1.0.1": 36
      },
      "greatertwincities": {
        "v1.0.0": 36
      },
      "jacksonville": {
        "1.0.0": 35
      },
      "jerusalem": {
        "v0.3.1": 36
      },
      "knoxville": {
        "1.1.0": 31,
        "1.1.1": 6
      },
      "los-angeles-county": {
        "1.0.0": 36
      },
      "louisville": {
        "1.0.0": 36
      },
      "madrid": {
        "1.0.0": 1,
        "1.0.1": 6
      },
      "memphis": {
        "1.1.0": 35
      },
      "mfn-hamptonroads": {
        "1.0.0": 36
      },
      "mfn-hong-kong": {
        "0.3.0": 32,
        "0.4.0": 35
      },
      "mfn-lasvegas": {
        "1.1.0": 16
      },
      "mfn-madisonwi": {
        "3.0.0": 37
      },
      "mfn-northwestar": {
        "1.0.0": 36
      },
      "milan": {
        "1.0.0": 28
      },
      "monterrey": {
        "1.0.0": 2
      },
      "montreal": {
        "1.0.1": 31,
        "1.1.3": 35
      },
      "naples": {
        "1.0.0": 29
      },
      "nashville": {
        "2.0.0": 36
      },
      "oklahoma-city": {
        "1.0.0": 6
      },
      "orange-county": {
        "1.0.3": 35
      },
      "orlando": {
        "1.1.1": 25
      },
      "ottawa": {
        "1.0.1": 31,
        "1.1.3": 35
      },
      "palermo": {
        "1.0.0": 35
      },
      "pianura-emiliana": {
        "1.0.0": 14
      },
      "pianura-veneta": {
        "1.0.0": 14
      },
      "piedmont-triad": {
        "v1.0.0": 8
      },
      "providence": {
        "1.0.0": 36
      },
      "puerto-rico": {
        "1.0.1": 23
      },
      "quebec-city": {
        "1.0.1": 31,
        "1.1.3": 35
      },
      "richmond": {
        "1.1.0": 35
      },
      "riviera-romagnola": {
        "1.0.0": 28
      },
      "rochester": {
        "1.1.0": 35
      },
      "rome": {
        "1.0.0": 35
      },
      "rotterdam-the-hague": {
        "1.0.0": 35
      },
      "sacramento": {
        "1.0.0": 36
      },
      "san-antonio": {
        "1.1.1": 23
      },
      "san-juan": {
        "1.0.0": 22
      },
      "santa-barbara": {
        "1.0.1": 35
      },
      "singapore-val": {
        "1.0.0": 30
      },
      "south-florida": {
        "v1.0.0": 2
      },
      "spokane": {
        "1.0.0": 4,
        "2.0.0": 4,
        "2.1.0": 8
      },
      "sydney": {
        "1.0.0": 15,
        "1.1.0": 15,
        "1.2.0": 18
      },
      "tampa-bay": {
        "1.1.0": 35
      },
      "tel-aviv": {
        "v1.2.0": 32,
        "v1.3.0": 32,
        "v2.0.0": 36
      },
      "toronto": {
        "1.0.1": 31,
        "1.1.3": 35
      },
      "trondheim-val": {
        "1.0.0": 30
      },
      "turin": {
        "1.0.0": 35
      },
      "valencia": {
        "1.0.0": 1,
        "1.0.1": 6
      },
      "vancouver": {
        "1.0.1": 31,
        "1.1.3": 35
      },
      "warsaw-val": {
        "1.0.0": 30
      },
      "waterloo": {
        "1.0.0": 32,
        "1.0.1": 32,
        "1.1.0": 25
      },
      "wilmington-nc": {
        "v1.0.0": 6
      },
      "winnipeg": {
        "1.0.1": 31,
        "1.1.3": 35
      },
      "yukina-fukuoka": {
        "0.2.0": 31,
        "0.3.0": 30,
        "0.4.0": 16
      },
      "yukina-hakodate": {
        "0.1.0": 30,
        "0.2.0": 16
      },
      "yukina-hiroshima-kure": {
        "0.2.0": 31,
        "0.3.0": 30,
        "0.4.0": 16
      },
      "yukina-kagoshima-kirishima": {
        "0.2.0": 31,
        "0.3.0": 30,
        "0.4.0": 16
      },
      "yukina-kitakyushu-shimonoseki": {
        "0.2.0": 31,
        "0.3.0": 30,
        "0.4.0": 16
      },
      "yukina-kobe-akashi": {
        "0.2.0": 31,
        "0.3.0": 30,
        "0.4.0": 16
      },
      "yukina-kochi": {
        "0.2.0": 31,
        "0.3.0": 30,
        "0.4.0": 16
      },
      "yukina-kyoto": {
        "0.2.0": 31,
        "0.3.0": 30,
        "0.4.0": 16
      },
      "yukina-matsuyama": {
        "0.2.0": 31,
        "0.3.0": 30,
        "0.4.0": 16
      },
      "yukina-nagasaki": {
        "0.1.0": 30,
        "0.2.0": 16
      },
      "yukina-nagoya": {
        "0.1.4": 8
      },
      "yukina-nakaumi": {
        "0.1.0": 30,
        "0.2.0": 16
      },
      "yukina-niigata": {
        "0.2.0": 31,
        "0.3.0": 30,
        "0.4.0": 16
      },
      "yukina-okayama": {
        "0.1.0": 16
      },
      "yukina-okinawa": {
        "0.2.0": 31,
        "0.3.0": 30,
        "0.4.0": 16
      },
      "yukina-osaka": {
        "0.1.0": 12,
        "0.1.1": 4,
        "0.1.2": 8
      },
      "yukina-sapporo-chitose": {
        "0.2.0": 31,
        "0.3.0": 30,
        "0.4.0": 16
      },
      "yukina-sendai": {
        "0.2.0": 31,
        "0.3.0": 30,
        "0.4.0": 16
      },
      "yukina-takamatsu": {
        "0.1.0": 30,
        "0.2.0": 16
      },
      "yukina-toyama": {
        "0.1.0": 30,
        "0.2.0": 16
      },
      "yukina-yamagata": {
        "0.2.0": 31,
        "0.3.0": 30,
        "0.4.0": 16
      },
      "zurich": {
        "v1.0.0": 32,
        "v1.1.0": 36
      }
    },
    "total_downloads": 11369,
    "raw_total_downloads": 15292,
    "total_attributed_downloads": 3923,
    "net_downloads": 535,
    "source_downloads_mode": "already_adjusted",
    "index": {
      "schema_version": 1,
      "maps": [
        "albany",
        "amsterdam",
        "anchorage-ak",
        "baltimore-dc-corridor",
        "barcelona",
        "bari",
        "berlin-val",
        "bilbao",
        "bologna",
        "bucharest-medium",
        "cairo",
        "calgary",
        "catania",
        "charleston-huntington-wv",
        "colorado-ski-country",
        "dayton-oh",
        "daytonatti",
        "dublin",
        "edmonton",
        "florence",
        "garda-lake",
        "genoa",
        "glasgow-edinburgh",
        "greater-baltimore",
        "greater-kuala-lumpur",
        "greater-los-angeles",
        "greatertwincities",
        "jacksonville",
        "jerusalem",
        "knoxville",
        "los-angeles-county",
        "louisville",
        "madrid",
        "memphis",
        "mfn-hamptonroads",
        "mfn-hong-kong",
        "mfn-lasvegas",
        "mfn-madisonwi",
        "mfn-northwestar",
        "milan",
        "monterrey",
        "montreal",
        "naples",
        "nashville",
        "oklahoma-city",
        "orange-county",
        "orlando",
        "ottawa",
        "palermo",
        "pianura-emiliana",
        "pianura-veneta",
        "piedmont-triad",
        "providence",
        "puerto-rico",
        "quebec-city",
        "richmond",
        "riviera-romagnola",
        "rochester",
        "rome",
        "rotterdam-the-hague",
        "sacramento",
        "san-antonio",
        "san-juan",
        "santa-barbara",
        "singapore-val",
        "south-florida",
        "spokane",
        "sydney",
        "tampa-bay",
        "tel-aviv",
        "toronto",
        "trondheim-val",
        "turin",
        "valencia",
        "vancouver",
        "warsaw-val",
        "waterloo",
        "wilmington-nc",
        "winnipeg",
        "yukina-fukuoka",
        "yukina-hakodate",
        "yukina-hiroshima-kure",
        "yukina-kagoshima-kirishima",
        "yukina-kitakyushu-shimonoseki",
        "yukina-kobe-akashi",
        "yukina-kochi",
        "yukina-kyoto",
        "yukina-matsuyama",
        "yukina-nagasaki",
        "yukina-nagoya",
        "yukina-nakaumi",
        "yukina-niigata",
        "yukina-okayama",
        "yukina-okinawa",
        "yukina-osaka",
        "yukina-sapporo-chitose",
        "yukina-sendai",
        "yukina-takamatsu",
        "yukina-toyama",
        "yukina-yamagata",
        "zurich"
      ]
    },
    "entries": 101
  },
  "mods": {
    "downloads": {
      "advanced-analytics": {
        "v1.1.0": 560,
        "v1.2.0": 39,
        "v1.2.1": 306,
        "v1.2.5": 37,
        "v1.2.6": 1,
        "v1.2.7": 108,
        "v1.2.8": 118,
        "v1.2.9": 96,
        "v1.3.0": 78,
        "v1.3.1": 196,
        "v1.3.2": 306
      },
      "any-money": {
        "v0.1.0": 38,
        "v0.1.1": 102,
        "v0.2.0": 202
      },
      "cinematic-camera": {
        "v1.0.0": 11,
        "v1.1.0": 17,
        "v1.2.0": 273
      },
      "citymapper": {
        "0.1.2": 765
      },
      "danield1909-dantrains": {
        "v1.0.0": 15,
        "v1.0.1": 55,
        "v1.0.2": 81,
        "v1.0.3": 42,
        "v1.1.0": 26,
        "v1.1.1": 48,
        "v1.1.2": 21,
        "v1.2.0": 22,
        "v1.2.1": 62,
        "v1.3.0": 287
      },
      "dep-test-mod": {
        "0.1.3": 5
      },
      "dep-test-mod-nested": {
        "0.1.0": 10
      },
      "distance-circles": {
        "0.3.3": 203,
        "0.4.0": 378
      },
      "simple-trains": {
        "v1.0.0": 69
      },
      "station-dots": {
        "v1.0.0": 30
      },
      "subwaybuilder-regions": {
        "v0.4.5": 524
      },
      "test-mod-vulnscan": {},
      "transit-overlay": {
        "1.5.0": 486
      },
      "valdotoriums-trains": {
        "v0.1.3": 821,
        "v0.1.4": 524
      }
    },
    "raw_downloads": {
      "advanced-analytics": {
        "v1.1.0": 590,
        "v1.2.0": 66,
        "v1.2.1": 332,
        "v1.2.5": 49,
        "v1.2.6": 10,
        "v1.2.7": 117,
        "v1.2.8": 121,
        "v1.2.9": 99,
        "v1.3.0": 80,
        "v1.3.1": 197,
        "v1.3.2": 307
      },
      "any-money": {
        "v0.1.0": 57,
        "v0.1.1": 120,
        "v0.2.0": 205
      },
      "cinematic-camera": {
        "v1.0.0": 32,
        "v1.1.0": 35,
        "v1.2.0": 284
      },
      "citymapper": {
        "0.1.2": 791
      },
      "danield1909-dantrains": {
        "v1.0.0": 46,
        "v1.0.1": 83,
        "v1.0.2": 109,
        "v1.0.3": 66,
        "v1.1.0": 47,
        "v1.1.1": 67,
        "v1.1.2": 36,
        "v1.2.0": 35,
        "v1.2.1": 72,
        "v1.3.0": 293
      },
      "dep-test-mod": {
        "0.1.3": 12
      },
      "dep-test-mod-nested": {
        "0.1.0": 17
      },
      "distance-circles": {
        "0.3.3": 233,
        "0.4.0": 395
      },
      "simple-trains": {
        "v1.0.0": 70
      },
      "station-dots": {
        "v1.0.0": 31
      },
      "subwaybuilder-regions": {
        "v0.4.5": 554
      },
      "test-mod-vulnscan": {},
      "transit-overlay": {
        "1.5.0": 516
      },
      "valdotoriums-trains": {
        "v0.1.3": 849,
        "v0.1.4": 527
      }
    },
    "attributed_downloads": {
      "advanced-analytics": {
        "v1.1.0": 30,
        "v1.2.0": 27,
        "v1.2.1": 26,
        "v1.2.5": 12,
        "v1.2.6": 9,
        "v1.2.7": 9,
        "v1.2.8": 3,
        "v1.2.9": 3,
        "v1.3.0": 2,
        "v1.3.1": 1,
        "v1.3.2": 1
      },
      "any-money": {
        "v0.1.0": 19,
        "v0.1.1": 18,
        "v0.2.0": 3
      },
      "cinematic-camera": {
        "v1.0.0": 21,
        "v1.1.0": 18,
        "v1.2.0": 11
      },
      "citymapper": {
        "0.1.2": 26
      },
      "danield1909-dantrains": {
        "v1.0.0": 31,
        "v1.0.1": 28,
        "v1.0.2": 28,
        "v1.0.3": 24,
        "v1.1.0": 21,
        "v1.1.1": 19,
        "v1.1.2": 15,
        "v1.2.0": 13,
        "v1.2.1": 10,
        "v1.3.0": 6
      },
      "dep-test-mod": {
        "0.1.3": 7
      },
      "dep-test-mod-nested": {
        "0.1.0": 7
      },
      "distance-circles": {
        "0.3.3": 30,
        "0.4.0": 17
      },
      "simple-trains": {
        "v1.0.0": 1
      },
      "station-dots": {
        "v1.0.0": 1
      },
      "subwaybuilder-regions": {
        "v0.4.5": 30
      },
      "test-mod-vulnscan": {},
      "transit-overlay": {
        "1.5.0": 30
      },
      "valdotoriums-trains": {
        "v0.1.3": 28,
        "v0.1.4": 3
      }
    },
    "total_downloads": 6962,
    "raw_total_downloads": 7550,
    "total_attributed_downloads": 588,
    "net_downloads": 509,
    "source_downloads_mode": "already_adjusted",
    "index": {
      "schema_version": 1,
      "mods": [
        "advanced-analytics",
        "any-money",
        "cinematic-camera",
        "citymapper",
        "danield1909-dantrains",
        "dep-test-mod",
        "dep-test-mod-nested",
        "distance-circles",
        "simple-trains",
        "station-dots",
        "subwaybuilder-regions",
        "test-mod-vulnscan",
        "transit-overlay",
        "valdotoriums-trains"
      ]
    },
    "entries": 14
  }
}
