{
  "schema_version": 2,
  "delta_id": "24257590377:generate-maps:map:full",
  "source": "workflow:Regenerate Registry Analytics (Full):map:full",
  "generated_at": "2026-04-10T18:20:42.448Z",
  "assets": {
    "maximilian284/subwaybuilder-es-maps@1.0.2/esbc.zip#RA_kwDOR1-vdM4XdBRP": 1,
    "maximilian284/subwaybuilder-es-maps@1.0.2/esbi.zip#RA_kwDOR1-vdM4XdBRR": 1,
    "maximilian284/subwaybuilder-es-maps@1.0.2/esmd.zip#RA_kwDOR1-vdM4XdBRQ": 1,
    "maximilian284/subwaybuilder-es-maps@1.0.2/esva.zip#RA_kwDOR1-vdM4XdBRS": 1
  }
}
